mcp_server_jerryni_demo/__init__.py
mcp_server_jerryni_demo-0.1.0.dist-info/METADATA
mcp_server_jerryni_demo-0.1.0.dist-info/WHEEL
mcp_server_jerryni_demo-0.1.0.dist-info/entry_points.txt
mcp_server_jerryni_demo-0.1.0.dist-info/RECORD
